CrowdClient/__init__.py
CrowdClient/crowdclient.py
CrowdClient/helpers.py
CrowdClient-0.1.0.dist-info/LICENSE
CrowdClient-0.1.0.dist-info/METADATA
CrowdClient-0.1.0.dist-info/WHEEL
CrowdClient-0.1.0.dist-info/top_level.txt
CrowdClient-0.1.0.dist-info/RECORD
