Metadata-Version: 2.1
Name: CrowdClient
Version: 0.1.0
Summary: CrowdClient is a Python library for interacting with CrowdStrike Falcon's REST API.
Home-page: https://github.com/tyler-tee/CrowdClient
Author: Tyler Talaga
Author-email: ttalaga@wgu.edu
License: GPLv3
Platform: UNKNOWN
